{"slug":"the-supreme-immortal-emperor","title":{"en":"The Supreme Immortal Emperor","km":"бһҖбҹҶбһ–бһјбһӣбһўбһ’бһ·бһҡбһ¶бһҮбһўбһҳбһҸбҹҲ"},"description":{"en":"When a modern-day scientist time-travels to an ancient martial arts world, he becomes a master at a prestigious cultivation academy. Finding his female students weak and underestimated, he uses modern technology, physics, and scientific training methods to transform them into the strongest warriors in the school. Breaking traditional norms, they defeat every arrogant male competitor in the arena, while he wins their hearts and eventually marries them. Watch this hilarious, action-packed, and satisfying xianxia drama of science conquering ancient cultivation!","km":"бһ“бҹ…бһ–бҹҒбһӣбһҠбҹӮбһӣбһўбҹ’бһ“бһҖбһңбһ·бһ‘бҹ’бһҷбһ¶бһҹбһ¶бһҹбҹ’бһҸбҹ’бһҡбһҹбһҳбҹҗбһҷбһ‘бҹҶбһ“бһҫбһ”бһҳбҹ’бһ“бһ¶бһҖбҹӢбһ”бһ¶бһ“бһҶбҹ’бһӣбһ„бһ—бһ–бһ‘бҹ…бһҖбһ¶бһ“бҹӢбһ–бһ·бһ—бһ–бһӮбһ»бһ“бһ”бһ»бһҡбһ¶бһҺ бһӮбҹҒбһ”бһ¶бһ“бһҖбҹ’бһӣбһ¶бһҷбһҮбһ¶бһӮбҹ’бһҡбһјбһ”бһ„бҹ’бһҡбҹҖбһ“бһ“бҹ…бһҖбҹ’бһ“бһ»бһ„бһҹбһ¶бһӣбһ¶бһ бҹ’бһңбһ№бһҖбһ бһ¶бһҸбҹӢбһҖбҹ’бһ”бһ¶бһ…бҹӢбһӮбһ»бһ“бһҳбһҪбһҷбҹ” бһҠбҹ„бһҷбһғбһҫбһүбһҹбһ·бһҹбҹ’бһҹбһҹбҹ’бһҡбһёбҹ—бһҡбһ”бһҹбҹӢбһҒбҹ’бһӣбһҪбһ“бһ‘бһ“бҹӢбһҒбҹ’бһҹбҹ„бһҷ бһ“бһ·бһ„бһҸбҹ’бһҡбһјбһңбһӮбҹҒбһҳбһҫбһӣбһ„бһ¶бһҷ бһӮбҹҒбһ”бһ¶бһ“бһ”бҹ’бһҡбһҫбһ”бҹ’бһҡбһ¶бһҹбҹӢбһ”бһ…бҹ’бһ…бҹҒбһҖбһңбһ·бһ‘бҹ’бһҷбһ¶ бһ“бһ·бһ„бһ…бҹҶбһҺбҹҒбҹҮбһҠбһ№бһ„бһңбһ·бһ‘бҹ’бһҷбһ¶бһҹбһ¶бһҹбҹ’бһҸбҹ’бһҡбһҹбһҳбҹҗбһҷбһҗбҹ’бһҳбһё бһҠбһҫбһҳбҹ’бһ”бһёбһ бҹ’бһңбһ№бһҖбһ бһ¶бһҸбҹӢбһ–бһҪбһҖбһӮбҹҒбһұбҹ’бһҷбһҖбҹ’бһӣбһ¶бһҷбһҮбһ¶бһўбҹ’бһ“бһҖбһҒбҹ’бһӣбһ¶бҹҶбһ„бһ–бһјбһҖбҹӮбһӮбҹ’бһҳбһ¶бһ“бһӮбһјбһ”бҹ’бһҡбҹҖбһ”бҹ” бһ–бһҪбһҖбһӮбҹҒбһ”бһ¶бһ“бһңбһ¶бһҷбһ”бһҖ бһ“бһ·бһ„бһҷбһҖбһҲбҹ’бһ“бҹҮбһҡбһ¶бһӣбҹӢбһӮбһјбһ”бҹ’бһҡбһҮбҹӮбһ„бһ”бһ»бһҡбһҹбҹ—бһ“бҹ…бһҖбҹ’бһ“бһ»бһ„бһҹбһ¶бһӣбһ¶бһӮбһ»бһ“ бһ бһҫбһҷбһҡбһјбһ”бһӮбҹҒбһҖбҹҸбһ”бһ¶бһ“бһҡбҹҖбһ”бһҖбһ¶бһҡбһҮбһ¶бһҳбһҪбһҷбһҹбһ·бһҹбҹ’бһҹбһҹбҹ’бһҡбһёбҹ—бһ‘бһ¶бҹҶбһ„бһ“бҹ„бҹҮбһ•бһ„бһҠбҹӮбһҡбҹ” бһҹбһјбһҳбһ‘бһҹбҹ’бһҹбһ“бһ¶бһҡбһҝбһ„бһ—бһ¶бһӮбһ”бҹӮбһ”бһҖбҹҶбһ”бҹ’бһӣбҹӮбһ„ бһ“бһ·бһ„бһ”бҹ’бһӣбҹӮбһҖбһ—бҹ’бһ“бҹӮбһҖбһ“бҹғбһҖбһ¶бһҡбһ”бҹ’бһҡбһҫбһңбһ·бһ‘бҹ’бһҷбһ¶бһҹбһ¶бһҹбҹ’бһҸбҹ’бһҡбһҷбһҖбһҲбҹ’бһ“бҹҮбһӣбһҫбһҳбһ бһ·бһ‘бҹ’бһ’бһ·бһ«бһ‘бҹ’бһ’бһ·бһ”бһ»бһҡбһ¶бһҺ!"},"poster":"./assets/images/the-supreme-immortal-emperor.png","year":2024,"rating":8.2,"genres":["ACTION","DRAMA","FANTASY","SHORTFILM"],"language":"Khmer","episodeCount":1,"episodes":[{"ep":"1","title":{"en":"Full Movie","km":"бһҳбһҪбһҷбһҡбһҝбһ„бһ–бҹҒбһү"},"url":"https://raw.githubusercontent.com/chamrong-thor/ishortvdos/vv/x/index.single","type":"M3U8","final":true}],"country":"China","enriched":true}
