{"slug":"the-god-of-cookery","title":{"en":"The God of Cookery","km":"бһ…бһ»бһ„бһҶбҹ…бһ‘бҹҒбһңбһҸбһ¶"},"description":{"en":"The world's most famous and feared chef lost his title as God of Cookery due to his good behavior. Due to his pain and reawakening, he sets out to reclaim his position.","km":"бһҳбҹҒбһ…бһ»бһ„бһ—бҹ…бһҠбҹҸбһӣбҹ’бһ”бһё бһ“бһ·бһ„бһӮбһҪбһҡбһұбҹ’бһҷбһҒбҹ’бһӣбһ¶бһ…бһ”бҹҶбһ•бһ»бһҸбһҖбҹ’бһ“бһ»бһ„бһ–бһ·бһ—бһ–бһӣбҹ„бһҖбһ”бһ¶бһҸбҹӢбһ”бһ„бҹӢбһ„бһ¶бһҡбһҮбһ¶ God of Cookery бһҠбҹ„бһҷбһҹбһ¶бһҡбһҸбҹӮбһўбһ¶бһҖбһ”бҹ’бһ”бһҖбһ·бһҡбһ·бһҷбһ¶бһӣбҹ’бһўбһҡбһ”бһҹбҹӢбһӮбһ¶бһҸбҹӢбҹ” бһҠбҹ„бһҷвҖӢбһҹбһ¶бһҡбһҸбҹӮбһ—бһ¶бһ–бһҲбһәбһ…бһ¶бһ”бҹӢ бһ“бһ·бһ„бһҖбһ¶бһҡбһ—бҹ’бһүбһ¶бһҖбҹӢбһҒбҹ’бһӣбһҪбһ“бһЎбһҫбһ„бһңбһ·бһү бһӮбһ¶бһҸбҹӢбһҖбҹҸвҖӢбһ…бҹҒбһүвҖӢбһ‘бҹ…вҖӢбһҠбһҺбҹ’бһҸбһҫбһҳвҖӢбһҷбһҖвҖӢбһҸбҹҶбһҺбҹӮбһ„вҖӢбһҡбһ”бһҹбҹӢвҖӢбһӮбһ¶бһҸбҹӢвҖӢбһЎбһҫбһ„вҖӢбһңбһ·бһүбҹ”"},"poster":"https://m.media-amazon.com/images/M/MV5BMWU1MjY2NTEtZjQyOC00MmM5LWJhYTktMGM4NzIxN2NkMGFjXkEyXkFqcGc@._V1_.jpg","year":1996,"rating":7.2,"genres":["COMEDY","ACTION","FANTASY","ROMANCE","DRAMA"],"language":"English","episodeCount":1,"episodes":[{"ep":"1","title":{"en":"Episode 1","km":"бһ—бһ¶бһӮбһ‘бһё1"},"url":"https://raw.githubusercontent.com/iamcleanerkak/comedyii/refs/heads/the-god-of-cookery/x/index.single","type":"M3U8","final":false}]}